k2_sandbox/__init__.py
k2_sandbox/charts.py
k2_sandbox/exceptions.py
k2_sandbox/filesystem.py
k2_sandbox/models.py
k2_sandbox/notebook.py
k2_sandbox/process.py
k2_sandbox/sandbox.py
k2_sandbox/terminal.py
k2_sandbox-0.1.2.dist-info/licenses/LICENSE
k2_sandbox-0.1.2.dist-info/METADATA
k2_sandbox-0.1.2.dist-info/WHEEL
k2_sandbox-0.1.2.dist-info/top_level.txt
k2_sandbox-0.1.2.dist-info/RECORD
