Metadata-Version: 2.4
Name: k2-sandbox
Version: 0.1.2
Summary: Python SDK for running LLM-generated code in isolated Docker container environments
Author-email: K2 Team <info@k2sandbox.com>
License: MIT
Project-URL: Homepage, https://github.com/k2data/k2-sandbox
Project-URL: Bug Tracker, https://github.com/k2data/k2-sandbox/issues
Project-URL: Documentation, https://github.com/k2data/k2-sandbox#documentation
Classifier: Programming Language :: Python :: 3
Classifier: License :: OSI Approved :: MIT License
Classifier: Operating System :: OS Independent
Classifier: Development Status :: 4 - Beta
Classifier: Intended Audience :: Developers
Classifier: Topic :: Software Development :: Libraries :: Python Modules
Requires-Python: >=3.11
License-File: LICENSE
Requires-Dist: build>=1.2.2.post1
Requires-Dist: docker>=7.1.0
Requires-Dist: httpx>=0.28.1
Requires-Dist: python-dotenv>=1.1.0
Requires-Dist: twine>=6.1.0
Dynamic: license-file
